<?xml version="1.0" encoding="us-ascii"?>
<database name="hammerheart">
  <table name="subbrain_smart_area" version="1">
    <header>
      <column name="explicit_initialization" type="boolean" />
      <column name="file_name" type="character varying" />
      <column name="on_enter_tree" type="character varying" />
      <column name="on_exit_tree" type="character varying" />
      <column name="on_release_tree" type="character varying" />
      <column name="on_request_tree" type="character varying" />
      <column name="on_update_tree" type="character varying" />
      <column name="subbrain_id" type="uuid" />
      <column name="system_variables" type="boolean" />
    </header>
    <rows>
      <row explicit_initialization="" file_name="default.xml" on_enter_tree="" on_exit_tree="" on_release_tree="" on_request_tree="" on_update_tree="" subbrain_id="00000000-0000-0000-0000-000000070002" system_variables="" />
      <row explicit_initialization="" file_name="final/sa_city.xml" on_enter_tree="" on_exit_tree="" on_release_tree="" on_request_tree="" on_update_tree="CitySA_onUpdate" subbrain_id="00000000-0000-0000-0000-000000070021" system_variables="" />
      <row explicit_initialization="" file_name="final/sa_land.xml" on_enter_tree="" on_exit_tree="" on_release_tree="" on_request_tree="" on_update_tree="onUpdate" subbrain_id="00000000-0000-0000-0000-000000070023" system_variables="" />
      <row explicit_initialization="" file_name="final/sa_farm.xml" on_enter_tree="" on_exit_tree="" on_release_tree="" on_request_tree="" on_update_tree="" subbrain_id="00000000-0000-0000-0000-000000070026" system_variables="" />
      <row explicit_initialization="True" file_name="final/sa_fish.xml" on_enter_tree="" on_exit_tree="" on_release_tree="" on_request_tree="" on_update_tree="FishSA_onUpdate" subbrain_id="00000000-0000-0000-0000-000000070030" system_variables="" />
      <row explicit_initialization="" file_name="final/sa_smithy.xml" on_enter_tree="" on_exit_tree="" on_release_tree="" on_request_tree="" on_update_tree="SmithySA_onUpdate" subbrain_id="00000000-0000-0000-0000-000000070031" system_variables="" />
      <row explicit_initialization="" file_name="final/sa_home.xml" on_enter_tree="HomeSA_onEnter" on_exit_tree="" on_release_tree="" on_request_tree="" on_update_tree="HomeSA_onUpdate" subbrain_id="00000000-0000-0000-0000-000000070032" system_variables="" />
      <row explicit_initialization="" file_name="_qa/multitest.xml" on_enter_tree="" on_exit_tree="" on_release_tree="" on_request_tree="" on_update_tree="onUpdate" subbrain_id="078a7caa-ee50-4550-a62d-7a880b568c95" system_variables="" />
      <row explicit_initialization="" file_name="final/sam_shopping.xml" on_enter_tree="" on_exit_tree="" on_release_tree="rel" on_request_tree="req" on_update_tree="upd" subbrain_id="0985edb0-5f83-44e8-af72-e482de90bf82" system_variables="" />
      <row explicit_initialization="" file_name="final/sa_camp.xml" on_enter_tree="camp_onEnter" on_exit_tree="" on_release_tree="" on_request_tree="" on_update_tree="camp_onUpdate" subbrain_id="0b0ad675-39c2-4ba1-823a-f67be8ad73d6" system_variables="True" />
      <row explicit_initialization="" file_name="final/sa_garrison.xml" on_enter_tree="" on_exit_tree="" on_release_tree="onRelease" on_request_tree="" on_update_tree="onUpdate" subbrain_id="0bf952c1-492a-4906-bcd0-9d2fa90380f9" system_variables="" />
      <row explicit_initialization="" file_name="_j/router.xml" on_enter_tree="onEnter" on_exit_tree="onExit" on_release_tree="onRelease" on_request_tree="onRequest" on_update_tree="onUpdate" subbrain_id="128f55c2-c170-40e6-abd0-0ffc1e41bd97" system_variables="" />
      <row explicit_initialization="" file_name="_testing/combatWeapons.xml" on_enter_tree="" on_exit_tree="onExit" on_release_tree="" on_request_tree="" on_update_tree="onUpdate" subbrain_id="1aeb564f-d289-4237-ac85-17ee0f17a3f3" system_variables="" />
      <row explicit_initialization="" file_name="final/sa_shop.xml" on_enter_tree="" on_exit_tree="" on_release_tree="rel" on_request_tree="req" on_update_tree="" subbrain_id="1bdffe0b-89cc-4019-a5ea-f5e11764673b" system_variables="" />
      <row explicit_initialization="" file_name="final/sa_duel.xml" on_enter_tree="onEnter" on_exit_tree="onExit" on_release_tree="onRelease" on_request_tree="onRequest" on_update_tree="onUpdate" subbrain_id="1c1151c8-c9ca-4aba-9489-46026ff78a27" system_variables="" />
      <row explicit_initialization="" file_name="autotest/codetest_synch.xml" on_enter_tree="Synch_onEnter" on_exit_tree="" on_release_tree="" on_request_tree="Synch_onRequest" on_update_tree="" subbrain_id="1cc64f75-e7b5-4e81-807f-5145e130cb95" system_variables="" />
      <row explicit_initialization="" file_name="_athert/codetest_expression.xml" on_enter_tree="test_exp_onEnter" on_exit_tree="" on_release_tree="" on_request_tree="" on_update_tree="" subbrain_id="1db0a019-9c19-40dd-9ed7-93b1cf2c070d" system_variables="" />
      <row explicit_initialization="" file_name="final/sa_nightingale1.xml" on_enter_tree="" on_exit_tree="" on_release_tree="" on_request_tree="" on_update_tree="" subbrain_id="20a3d413-4f1a-4d59-be76-abadb33a9755" system_variables="" />
      <row explicit_initialization="" file_name="final/sa_home.xml" on_enter_tree="" on_exit_tree="" on_release_tree="" on_request_tree="" on_update_tree="HomeSA_onUpdate" subbrain_id="21ddddac-bdf6-4be8-8510-6ddb44273cbe" system_variables="" />
      <row explicit_initialization="" file_name="_j/Sheep.xml" on_enter_tree="" on_exit_tree="" on_release_tree="" on_request_tree="" on_update_tree="" subbrain_id="22809877-e18f-43c9-815d-d0f1cc48858d" system_variables="" />
      <row explicit_initialization="" file_name="_qa/test_repro.xml" on_enter_tree="onEnter" on_exit_tree="onExit" on_release_tree="onRelease" on_request_tree="onRequest" on_update_tree="onUpdate" subbrain_id="24759a5c-3fb9-45cf-9f28-1f08dec80525" system_variables="" />
      <row explicit_initialization="" file_name="_pepa/sa_test_pepa0.xml" on_enter_tree="onEnter" on_exit_tree="onExit" on_release_tree="" on_request_tree="" on_update_tree="onUpdate" subbrain_id="25ece455-5c1e-4478-932f-9f5adcfde37c" system_variables="" />
      <row explicit_initialization="" file_name="autotest/codetest_ifelsecondition.xml" on_enter_tree="onEnter" on_exit_tree="" on_release_tree="" on_request_tree="" on_update_tree="" subbrain_id="2777919f-de6c-4e68-94aa-3d383a101ec4" system_variables="" />
      <row explicit_initialization="" file_name="_j/horserace.xml" on_enter_tree="enter" on_exit_tree="" on_release_tree="" on_request_tree="" on_update_tree="" subbrain_id="2a21676a-acc5-4746-9dc4-ce71b7186de6" system_variables="" />
      <row explicit_initialization="" file_name="_mff.ai/test_sitting.xml" on_enter_tree="" on_exit_tree="" on_release_tree="" on_request_tree="onRequest" on_update_tree="" subbrain_id="2b89d493-8a54-41ec-82d7-8b7f1bc67344" system_variables="" />
      <row explicit_initialization="" file_name="_mz/martin_test_1.xml" on_enter_tree="" on_exit_tree="" on_release_tree="" on_request_tree="" on_update_tree="onUpdate" subbrain_id="32a81e39-21e5-4dcb-91c7-bc57c786b639" system_variables="" />
      <row explicit_initialization="" file_name="_dan/sa_test_surrender.xml" on_enter_tree="" on_exit_tree="" on_release_tree="" on_request_tree="" on_update_tree="onUpdate" subbrain_id="33d2127c-a9ec-430e-9e76-56f676ae2c60" system_variables="" />
      <row explicit_initialization="" file_name="autotest/codetest_pickup.xml" on_enter_tree="pickup_onEnter" on_exit_tree="" on_release_tree="" on_request_tree="" on_update_tree="" subbrain_id="39f9ca1a-75e8-4717-8d76-d3013f381cf0" system_variables="" />
      <row explicit_initialization="" file_name="_athert/test_sa_athert.xml" on_enter_tree="" on_exit_tree="" on_release_tree="" on_request_tree="" on_update_tree="onUpdatePMan" subbrain_id="3b17ed0c-fd27-4a22-bed9-c00f677828e5" system_variables="" />
      <row explicit_initialization="" file_name="final/sa_keep.xml" on_enter_tree="" on_exit_tree="" on_release_tree="" on_request_tree="" on_update_tree="onUpdate" subbrain_id="3b256be2-4058-40db-9752-2f6316d4e482" system_variables="" />
      <row explicit_initialization="" file_name="_malac/test_sa_malac.xml" on_enter_tree="" on_exit_tree="onExit" on_release_tree="" on_request_tree="" on_update_tree="onUpdate" subbrain_id="3e0767bc-7e12-4c3f-a090-a631d1a6ac3c" system_variables="" />
      <row explicit_initialization="" file_name="quests/q_Package.xml" on_enter_tree="FDenter" on_exit_tree="" on_release_tree="" on_request_tree="" on_update_tree="" subbrain_id="40313c8b-adfd-2b76-04b3-c7ba9dacb286" system_variables="" />
      <row explicit_initialization="" file_name="_mz/sa_test_stealth.xml" on_enter_tree="" on_exit_tree="" on_release_tree="" on_request_tree="" on_update_tree="onUpdate" subbrain_id="40479727-c88f-76f3-72e1-d734fbe5adaa" system_variables="" />
      <row explicit_initialization="" file_name="quests/q_returnToSkalitz.xml" on_enter_tree="" on_exit_tree="" on_release_tree="" on_request_tree="" on_update_tree="eventUpdate" subbrain_id="407ec63f-c4a6-3508-bd50-949eefcf0f93" system_variables="" />
      <row explicit_initialization="" file_name="_smejki/sa_smejkihoTest.xml" on_enter_tree="" on_exit_tree="" on_release_tree="onRelease" on_request_tree="onRequest" on_update_tree="onUpdate" subbrain_id="4098883d-230f-dd27-5e19-3f3d3f2a939d" system_variables="" />
      <row explicit_initialization="" file_name="final/sa_embroider.xml" on_enter_tree="" on_exit_tree="" on_release_tree="" on_request_tree="" on_update_tree="" subbrain_id="40c58a2f-76a5-60c5-4eb6-fc7df2f4c181" system_variables="" />
      <row explicit_initialization="" file_name="final/sa_event_tournamentAmbush.xml" on_enter_tree="" on_exit_tree="" on_release_tree="" on_request_tree="" on_update_tree="onUpdate" subbrain_id="41170fe0-7513-7678-0dce-3a32fc31e299" system_variables="" />
      <row explicit_initialization="" file_name="autotest/test_messages.xml" on_enter_tree="enter" on_exit_tree="" on_release_tree="" on_request_tree="" on_update_tree="" subbrain_id="411ba03e-55f5-210b-0f3f-11597074d6aa" system_variables="" />
      <row explicit_initialization="" file_name="final/sa_event_ambushPLR.xml" on_enter_tree="" on_exit_tree="" on_release_tree="" on_request_tree="" on_update_tree="onUpdate" subbrain_id="41261689-7cce-cd94-86aa-4016042f0489" system_variables="" />
      <row explicit_initialization="" file_name="_common/sa_test_perception.xml" on_enter_tree="" on_exit_tree="" on_release_tree="" on_request_tree="" on_update_tree="onUpdate" subbrain_id="414320de-184c-5df7-71b1-02f4abd7efb0" system_variables="" />
      <row explicit_initialization="" file_name="_ml/sa_test_homeLabut.xml" on_enter_tree="onEnter" on_exit_tree="" on_release_tree="onRelease" on_request_tree="onRequest" on_update_tree="onUpdate" subbrain_id="41916522-3c02-0206-aaec-81e47875f8b1" system_variables="" />
      <row explicit_initialization="" file_name="final/sa_lane_battle.xml" on_enter_tree="" on_exit_tree="" on_release_tree="" on_request_tree="onRequestMain" on_update_tree="onUpdateMain" subbrain_id="41968f8e-3980-eddd-34c9-c25c4ca6b2b7" system_variables="" />
      <row explicit_initialization="" file_name="_mz/eventTest.xml" on_enter_tree="" on_exit_tree="" on_release_tree="sa_onRelease" on_request_tree="sa_onRequest" on_update_tree="sa_onUpdate" subbrain_id="4199c7b6-f1e7-7260-b8cf-6d8280436389" system_variables="" />
      <row explicit_initialization="" file_name="sa_neuhof_colliers_gingerHideout" on_enter_tree="" on_exit_tree="" on_release_tree="onRelease" on_request_tree="onRequest" on_update_tree="onUpdate" subbrain_id="419c8ada-4a66-8dc8-ce8a-ec4f9f996fb6" system_variables="" />
      <row explicit_initialization="" file_name="final/sa_corpseCleaner.xml" on_enter_tree="" on_exit_tree="" on_release_tree="" on_request_tree="" on_update_tree="onUpdate" subbrain_id="419e5466-fb2e-2456-7df4-329d74c277b1" system_variables="" />
      <row explicit_initialization="" file_name="autotest/codetest_linknetwork.xml" on_enter_tree="onEnter" on_exit_tree="" on_release_tree="" on_request_tree="" on_update_tree="" subbrain_id="41b61774-9f04-25d2-6317-05c029625eb4" system_variables="" />
      <row explicit_initialization="" file_name="_pepa/sa_test_dummy.xml" on_enter_tree="" on_exit_tree="" on_release_tree="onRelease" on_request_tree="onRequest" on_update_tree="onUpdate" subbrain_id="41b85095-e7ed-4b45-dac5-461d5ca02ea3" system_variables="" />
      <row explicit_initialization="" file_name="_mz/daycycles.xml" on_enter_tree="" on_exit_tree="" on_release_tree="" on_request_tree="" on_update_tree="" subbrain_id="41ba32bb-71e7-cb03-d8f7-5d7079f360bc" system_variables="" />
      <row explicit_initialization="" file_name="_testing/sa_graphsearch_examples.xml" on_enter_tree="" on_exit_tree="" on_release_tree="" on_request_tree="" on_update_tree="onUpdate" subbrain_id="41cd5bc7-bc1f-1e0f-c1e5-c9110f0018ab" system_variables="" />
      <row explicit_initialization="" file_name="autotest/NameSender.xml" on_enter_tree="onEnter" on_exit_tree="onExit" on_release_tree="onRel" on_request_tree="onReq" on_update_tree="onUpdt" subbrain_id="41d20199-2ec0-faac-d537-8eb17b0beeab" system_variables="" />
      <row explicit_initialization="" file_name="final/archery_tourney.xml" on_enter_tree="" on_exit_tree="" on_release_tree="" on_request_tree="" on_update_tree="updtPot" subbrain_id="41d3a1b3-bef5-5d91-fcff-071588545781" system_variables="" />
      <row explicit_initialization="" file_name="_vp/test_house_uberlod.xml" on_enter_tree="" on_exit_tree="" on_release_tree="" on_request_tree="" on_update_tree="" subbrain_id="41e7cf8d-757e-4887-bd7e-886e617a03a1" system_variables="" />
      <row explicit_initialization="" file_name="final/sa_monastery_garden.xml" on_enter_tree="" on_exit_tree="" on_release_tree="" on_request_tree="" on_update_tree="" subbrain_id="42024cd9-ad50-76cb-c64e-e07d10040787" system_variables="" />
      <row explicit_initialization="" file_name="final/sa_monastery_dormitorium.xml" on_enter_tree="" on_exit_tree="" on_release_tree="" on_request_tree="" on_update_tree="" subbrain_id="42cb6362-bb94-ed5b-eb7d-a0bff86aad82" system_variables="" />
      <row explicit_initialization="" file_name="final/sa_trespass.xml" on_enter_tree="" on_exit_tree="" on_release_tree="" on_request_tree="" on_update_tree="onUpdate" subbrain_id="42d5e0ee-56e1-ea88-bfb8-92dee571089a" system_variables="" />
      <row explicit_initialization="" file_name="_smejki/test_waitstring_bug.xml" on_enter_tree="" on_exit_tree="" on_release_tree="" on_request_tree="" on_update_tree="onUpdate" subbrain_id="42fb1edf-3fa1-514e-492c-ac2d9abb9ea8" system_variables="" />
      <row explicit_initialization="" file_name="autotest/TestNavigation.xml" on_enter_tree="sa_onEnter" on_exit_tree="" on_release_tree="" on_request_tree="" on_update_tree="" subbrain_id="43bc51de-4062-7d4b-df62-cb7502b241b9" system_variables="True" />
      <row explicit_initialization="" file_name="_smejki/sa_test_js_banditCamp.xml" on_enter_tree="onEnter" on_exit_tree="onExit" on_release_tree="onRelease" on_request_tree="onRequest" on_update_tree="onUpdate" subbrain_id="43fdf087-d623-4c24-bf43-48127c441c88" system_variables="" />
      <row explicit_initialization="" file_name="quests/q_basicTraining.xml" on_enter_tree="sa_onEnter" on_exit_tree="sa_onExit" on_release_tree="" on_request_tree="" on_update_tree="" subbrain_id="442a6a9e-efeb-4f42-8b9d-0121afcd21b0" system_variables="" />
      <row explicit_initialization="" file_name="final/sa_armory.xml" on_enter_tree="" on_exit_tree="" on_release_tree="" on_request_tree="" on_update_tree="" subbrain_id="4442258e-ebdd-ada8-b23b-4a51c4a4bc8f" system_variables="" />
      <row explicit_initialization="" file_name="_mz/sa_test_victim.xml" on_enter_tree="" on_exit_tree="" on_release_tree="" on_request_tree="" on_update_tree="onUpdate" subbrain_id="44642b75-4a3e-1da1-916c-be2396b78d8a" system_variables="" />
      <row explicit_initialization="" file_name="_mff.ai/SA_Walk.xml" on_enter_tree="" on_exit_tree="" on_release_tree="" on_request_tree="SA_Walk_onRequest" on_update_tree="SA_Walk_onUpdate" subbrain_id="446ed7b8-d46a-4eef-97a3-25aaf82e8a2b" system_variables="" />
      <row explicit_initialization="" file_name="_common/sa_test_playerState.xml" on_enter_tree="" on_exit_tree="" on_release_tree="" on_request_tree="" on_update_tree="onUpdate" subbrain_id="44a41ffe-a549-8485-7197-76afb07c4a9c" system_variables="" />
      <row explicit_initialization="" file_name="_jarda/sa_test_jarda.xml" on_enter_tree="" on_exit_tree="" on_release_tree="" on_request_tree="" on_update_tree="onUpdate" subbrain_id="44a5746d-a1d8-c97a-55c1-9845d9da838d" system_variables="True" />
      <row explicit_initialization="" file_name="quests/q_Brocade.xml" on_enter_tree="sa_clothShop_onEnter" on_exit_tree="sa_clothShop_onExit" on_release_tree="sa_clothShop_onRelease" on_request_tree="sa_clothShop_onRequest" on_update_tree="sa_clothShop_onUpdate" subbrain_id="44cd644b-d2e1-e3c8-e9da-264c1b829988" system_variables="" />
      <row explicit_initialization="" file_name="_pepa/sa_test_guards.xml" on_enter_tree="" on_exit_tree="" on_release_tree="onRelease" on_request_tree="onRequest" on_update_tree="onUpdate" subbrain_id="44ce62ad-e121-08d6-20bc-d4da4a960aaa" system_variables="" />
      <row explicit_initialization="" file_name="final/sa_eventMeeting.xml" on_enter_tree="" on_exit_tree="" on_release_tree="" on_request_tree="" on_update_tree="onUpdate" subbrain_id="44da65df-1cd4-c31b-1cb1-386200bf428a" system_variables="" />
      <row explicit_initialization="" file_name="final/sa_burning_hay.xml" on_enter_tree="onEnter" on_exit_tree="onExit" on_release_tree="" on_request_tree="" on_update_tree="onUpdate" subbrain_id="44e98716-a492-4c2e-cfc1-33ec23de18bb" system_variables="" />
      <row explicit_initialization="" file_name="final\sa_event_wanderer.xml" on_enter_tree="" on_exit_tree="" on_release_tree="" on_request_tree="onRequest" on_update_tree="onUpdate" subbrain_id="4512bb98-ff95-8e3e-3029-175f57a8d291" system_variables="" />
      <row explicit_initialization="" file_name="_ts/sa_test_tereza_2.xml" on_enter_tree="onEnter" on_exit_tree="" on_release_tree="" on_request_tree="" on_update_tree="" subbrain_id="451da004-9077-771c-f524-e116ae2adc94" system_variables="" />
      <row explicit_initialization="" file_name="_dan/sa_DanTest_Farmer.xml" on_enter_tree="" on_exit_tree="" on_release_tree="" on_request_tree="" on_update_tree="sa_DanTest_Farmer_onUpdate" subbrain_id="4522e2bd-77f8-4f59-d004-9f85f4ffbd9a" system_variables="" />
      <row explicit_initialization="" file_name="final/sa_district.xml" on_enter_tree="onEnter" on_exit_tree="" on_release_tree="" on_request_tree="" on_update_tree="onUpdate" subbrain_id="454e9f71-28d7-ccfc-ff49-68c6c31e84b0" system_variables="" />
      <row explicit_initialization="" file_name="quests/TA04_OurLittleHouse.xml" on_enter_tree="" on_exit_tree="" on_release_tree="" on_request_tree="" on_update_tree="" subbrain_id="456c8269-95b0-1f6b-8a34-dd988cd8e3bc" system_variables="" />
      <row explicit_initialization="" file_name="final/sa_court.xml" on_enter_tree="" on_exit_tree="" on_release_tree="" on_request_tree="" on_update_tree="onUpdate" subbrain_id="45ed72cb-d884-97e7-d7cf-d78c5a692ea7" system_variables="" />
      <row explicit_initialization="" file_name="quests/q_SikBas.xml" on_enter_tree="playermeat" on_exit_tree="" on_release_tree="" on_request_tree="" on_update_tree="" subbrain_id="45f9669d-9975-0938-d0ba-3e8b5f5cfc81" system_variables="" />
      <row explicit_initialization="" file_name="final/sa_monastery_priorRoom" on_enter_tree="" on_exit_tree="" on_release_tree="" on_request_tree="" on_update_tree="" subbrain_id="45fcb288-e5f9-da8f-268b-b35f7e0693b4" system_variables="" />
      <row explicit_initialization="" file_name="final/sa_pribyslavCamp.xml" on_enter_tree="" on_exit_tree="" on_release_tree="onRelease" on_request_tree="onRequest" on_update_tree="onUpdate" subbrain_id="461c74fa-1749-12e2-167f-446dd47456ad" system_variables="" />
      <row explicit_initialization="" file_name="_mz/sa_test_trespass.xml" on_enter_tree="" on_exit_tree="" on_release_tree="" on_request_tree="" on_update_tree="onUpdate" subbrain_id="464cc90f-7d5f-b788-4dfc-d1ac2cd310b4" system_variables="" />
      <row explicit_initialization="True" file_name="final/sa_kitchen.xml" on_enter_tree="" on_exit_tree="" on_release_tree="" on_request_tree="" on_update_tree="onUpdate" subbrain_id="4677015c-0bce-d9b7-5955-c71ba1c3fc80" system_variables="" />
      <row explicit_initialization="" file_name="final/sa_colliers.xml" on_enter_tree="" on_exit_tree="" on_release_tree="" on_request_tree="" on_update_tree="onUpdate" subbrain_id="469264ca-305a-dca5-721b-0988ab5696a2" system_variables="" />
      <row explicit_initialization="" file_name="_mz/sa_test_daycycleBehaviorClose.xml" on_enter_tree="" on_exit_tree="" on_release_tree="" on_request_tree="" on_update_tree="onUpdate" subbrain_id="46a5b07a-810a-58de-ba17-d44a04c3ebb8" system_variables="" />
      <row explicit_initialization="" file_name="_smejki/test_js_subbrainBehaviorSA.xml" on_enter_tree="onEnter" on_exit_tree="onExit" on_release_tree="onRelease" on_request_tree="onRequest" on_update_tree="onUpdate" subbrain_id="46d4ce61-b127-e590-a0f5-6f50e59677ae" system_variables="" />
      <row explicit_initialization="" file_name="autotest/codetest_spatialInfo.xml" on_enter_tree="entr" on_exit_tree="" on_release_tree="" on_request_tree="" on_update_tree="" subbrain_id="470097df-c8c1-7053-8d71-845fefb6878d" system_variables="" />
      <row explicit_initialization="" file_name="final/sa_gallows.xml" on_enter_tree="" on_exit_tree="" on_release_tree="" on_request_tree="" on_update_tree="" subbrain_id="470f9ecd-275f-760c-c9c7-690e3f5465bb" system_variables="" />
      <row explicit_initialization="" file_name="final/activityHorceRace.xml" on_enter_tree="sa_onEnter" on_exit_tree="sa_onExit" on_release_tree="" on_request_tree="" on_update_tree="" subbrain_id="472e5fb5-e058-40e1-8f3c-4db38f4ddd09" system_variables="" />
      <row explicit_initialization="" file_name="sa_test_js_MsgArea" on_enter_tree="" on_exit_tree="" on_release_tree="" on_request_tree="" on_update_tree="onUpdate" subbrain_id="47b898ae-582e-506e-211d-1a59db43b3b0" system_variables="" />
      <row explicit_initialization="" file_name="autotest/codetest_quest.xml" on_enter_tree="entr" on_exit_tree="" on_release_tree="" on_request_tree="" on_update_tree="" subbrain_id="48b81f64-3938-d828-bd6b-671680068fbf" system_variables="" />
      <row explicit_initialization="" file_name="final/sa_homeProhibitedArea.xml" on_enter_tree="" on_exit_tree="" on_release_tree="" on_request_tree="" on_update_tree="onUpdate" subbrain_id="48e35796-e1e2-870f-ee14-0aa232f7cd94" system_variables="" />
      <row explicit_initialization="" file_name="final/sa_monastery.xml" on_enter_tree="" on_exit_tree="" on_release_tree="" on_request_tree="" on_update_tree="onUpdate" subbrain_id="48eee547-20b7-6c6f-2134-41e54f16fb85" system_variables="" />
      <row explicit_initialization="" file_name="autotest/codetest_variables.xml" on_enter_tree="onEnter" on_exit_tree="onExit" on_release_tree="onRel" on_request_tree="onReq" on_update_tree="onUpdate" subbrain_id="49119bf5-b65d-6b8f-640a-a5bb267bc485" system_variables="" />
      <row explicit_initialization="" file_name="final/sa_gate.xml" on_enter_tree="" on_exit_tree="" on_release_tree="onRelease" on_request_tree="onRequest" on_update_tree="onUpdate" subbrain_id="49141268-eb10-9870-04e2-c326507a04a7" system_variables="" />
      <row explicit_initialization="" file_name="final/sa_shop2.xml" on_enter_tree="onEnter" on_exit_tree="onExit" on_release_tree="" on_request_tree="onRequest" on_update_tree="onUpdate" subbrain_id="491be845-104d-faa9-a076-564584754689" system_variables="" />
      <row explicit_initialization="" file_name="_mz/sa_test_shop_martin.xml" on_enter_tree="" on_exit_tree="" on_release_tree="" on_request_tree="" on_update_tree="onUpdate" subbrain_id="4967c588-9873-b441-dee8-7aedc0249ebb" system_variables="" />
      <row explicit_initialization="" file_name="_mz/sa_test_expectedTrespassArea.xml" on_enter_tree="" on_exit_tree="" on_release_tree="" on_request_tree="" on_update_tree="onUpdate" subbrain_id="49d177f4-e367-a374-22a1-be4972e4f7bb" system_variables="" />
      <row explicit_initialization="" file_name="final/sa_presence_alert.xml" on_enter_tree="onEnter" on_exit_tree="onExit" on_release_tree="" on_request_tree="" on_update_tree="onUpdate" subbrain_id="49ede974-9b6e-1817-50ce-b909b20177a9" system_variables="" />
      <row explicit_initialization="" file_name="final/sa_crimeDistrictRoot.xml" on_enter_tree="" on_exit_tree="" on_release_tree="" on_request_tree="" on_update_tree="onUpdate" subbrain_id="49fc34bc-6d00-4c82-68d5-6cd9314c81b3" system_variables="" />
      <row explicit_initialization="" file_name="quests/TA04_CumByMerh.xml" on_enter_tree="" on_exit_tree="" on_release_tree="" on_request_tree="" on_update_tree="" subbrain_id="4a47fb27-fb4a-9216-14cf-a1fa5b7c24a1" system_variables="" />
      <row explicit_initialization="" file_name="final/sa_monastery_refectory.xml" on_enter_tree="" on_exit_tree="" on_release_tree="" on_request_tree="" on_update_tree="main" subbrain_id="4a58cd9b-c888-a943-649b-5a3f972c13af" system_variables="" />
      <row explicit_initialization="" file_name="final\sa_event_city.xml" on_enter_tree="" on_exit_tree="" on_release_tree="" on_request_tree="onRequest" on_update_tree="onUpdate" subbrain_id="4a953b44-fb04-413f-ebd0-047123ff9ba7" system_variables="" />
      <row explicit_initialization="" file_name="final/sa_event_ambushNPC.xml" on_enter_tree="" on_exit_tree="" on_release_tree="" on_request_tree="" on_update_tree="onUpdate" subbrain_id="4aafe6b1-99de-7cf9-8856-2ef15263fa9b" system_variables="" />
      <row explicit_initialization="" file_name="quests\q_pribBattle.xml" on_enter_tree="bossOnEnter" on_exit_tree="" on_release_tree="" on_request_tree="" on_update_tree="" subbrain_id="4abf29c3-defb-afc7-52a4-b0c72058ea8c" system_variables="" />
      <row explicit_initialization="" file_name="_mz/sa_test_combatLock.xml" on_enter_tree="" on_exit_tree="" on_release_tree="" on_request_tree="" on_update_tree="onUpdate" subbrain_id="4b081e16-95f1-01bc-8d82-4ae02a69a2ae" system_variables="" />
      <row explicit_initialization="" file_name="final/sa_sleepover.xml" on_enter_tree="" on_exit_tree="" on_release_tree="" on_request_tree="" on_update_tree="onUpdate" subbrain_id="4b403fe9-4441-20de-7359-aa2dbf6e9981" system_variables="" />
      <row explicit_initialization="" file_name="_testing/test_sa_codeJirka.xml" on_enter_tree="" on_exit_tree="" on_release_tree="" on_request_tree="" on_update_tree="onUpdate" subbrain_id="4b7e7ea9-9307-2a65-0d58-d2414545f88e" system_variables="" />
      <row explicit_initialization="" file_name="autotest/test_smartobjects.xml" on_enter_tree="" on_exit_tree="" on_release_tree="" on_request_tree="" on_update_tree="onUpdateSA" subbrain_id="4bd83617-33c3-946f-8b39-c8c135f99eb6" system_variables="" />
      <row explicit_initialization="" file_name="final/sa_event_chase_manChasingThief.xml" on_enter_tree="" on_exit_tree="" on_release_tree="" on_request_tree="" on_update_tree="onUpdate" subbrain_id="4c3e2922-9796-d5fb-93e5-27d6187ee88c" system_variables="" />
      <row explicit_initialization="" file_name="final/archery_tourney.xml" on_enter_tree="" on_exit_tree="" on_release_tree="" on_request_tree="" on_update_tree="updtTarget" subbrain_id="4c3e5943-fe02-d49b-de3e-1e0782eaad95" system_variables="True" />
      <row explicit_initialization="" file_name="_viktor/combatTutorial.xml" on_enter_tree="" on_exit_tree="" on_release_tree="" on_request_tree="" on_update_tree="" subbrain_id="4c3f06c3-45e4-c083-b773-f8aae73842b9" system_variables="" />
      <row explicit_initialization="" file_name="_mz/test_waving.xml" on_enter_tree="" on_exit_tree="" on_release_tree="" on_request_tree="" on_update_tree="" subbrain_id="4c4b66d6-b098-549f-73cd-8b195aa7438e" system_variables="" />
      <row explicit_initialization="" file_name="final/sa_dream.xml" on_enter_tree="" on_exit_tree="" on_release_tree="" on_request_tree="" on_update_tree="onUpdate" subbrain_id="4c90e99e-3f37-a219-32e3-26ebd43ade86" system_variables="" />
      <row explicit_initialization="" file_name="_qa\test_playground_ls.xml" on_enter_tree="onEnter" on_exit_tree="" on_release_tree="" on_request_tree="" on_update_tree="onUpdate" subbrain_id="4cbda94a-2a50-14ef-48d4-25033f182bb5" system_variables="" />
      <row explicit_initialization="" file_name="_vita\sa_test_vita.xml" on_enter_tree="" on_exit_tree="" on_release_tree="" on_request_tree="" on_update_tree="" subbrain_id="4ce71cb7-fc68-91fa-c15b-e04283b9b5b6" system_variables="" />
      <row explicit_initialization="" file_name="final/sa_crimeDistrict.xml" on_enter_tree="onEnter" on_exit_tree="onExit" on_release_tree="" on_request_tree="" on_update_tree="onUpdate" subbrain_id="4cf683a4-b1dd-50af-fb77-6790c0667391" system_variables="" />
      <row explicit_initialization="" file_name="_ts/sa_test_tereza.xml" on_enter_tree="" on_exit_tree="" on_release_tree="" on_request_tree="" on_update_tree="onUpdate" subbrain_id="4cfc86a2-069b-a6ff-3184-df197bc689b8" system_variables="" />
      <row explicit_initialization="" file_name="_ml/sa_test_tools_slots.xml" on_enter_tree="" on_exit_tree="" on_release_tree="" on_request_tree="" on_update_tree="" subbrain_id="4d10883f-2883-29dc-f370-4403b9fa8abe" system_variables="" />
      <row explicit_initialization="" file_name="_ml/sa_test_gateFrisk.xml" on_enter_tree="onEnter" on_exit_tree="" on_release_tree="" on_request_tree="" on_update_tree="onUpdate" subbrain_id="4d14047a-61da-453b-5d3d-fb9ff886a9b7" system_variables="" />
      <row explicit_initialization="" file_name="final/sa_location.xml" on_enter_tree="" on_exit_tree="" on_release_tree="" on_request_tree="" on_update_tree="onUpdate" subbrain_id="4d14e62e-7026-06c1-2dfb-acbd2ca8b58a" system_variables="" />
      <row explicit_initialization="" file_name="final/sa_bakery.xml" on_enter_tree="" on_exit_tree="" on_release_tree="" on_request_tree="" on_update_tree="" subbrain_id="4d1fa0b2-b9fc-41a2-db5b-8332de19febc" system_variables="" />
      <row explicit_initialization="" file_name="_mz/crime.xml" on_enter_tree="" on_exit_tree="" on_release_tree="" on_request_tree="" on_update_tree="" subbrain_id="4d60f040-7a9e-0d27-a482-100000b07490" system_variables="" />
      <row explicit_initialization="" file_name="_mz/sa_test_hitReactions.xml" on_enter_tree="" on_exit_tree="" on_release_tree="" on_request_tree="" on_update_tree="onUpdate" subbrain_id="4d70fb66-69a2-aed0-2fd6-79ef335e8194" system_variables="" />
      <row explicit_initialization="" file_name="final/sa_infirmarium.xml" on_enter_tree="" on_exit_tree="" on_release_tree="" on_request_tree="" on_update_tree="onUpdate" subbrain_id="4da342f6-7042-131b-3eb2-5ca44a011a9b" system_variables="" />
      <row explicit_initialization="" file_name="final/sa_event_chase.xml" on_enter_tree="" on_exit_tree="" on_release_tree="" on_request_tree="" on_update_tree="onUpdate" subbrain_id="4daafae0-449e-54b7-e5f0-ee05d809668b" system_variables="" />
      <row explicit_initialization="" file_name="_smejki/sa_test_distGateCrashBug.xml" on_enter_tree="" on_exit_tree="" on_release_tree="" on_request_tree="" on_update_tree="onUpdate" subbrain_id="4df8a6be-5a15-4d79-f195-7773dad8e8bf" system_variables="" />
      <row explicit_initialization="" file_name="final/sa_event_roadsidecorpse.xml" on_enter_tree="onEnter" on_exit_tree="" on_release_tree="" on_request_tree="" on_update_tree="onUpdate" subbrain_id="4dfceea6-e548-fd05-8e54-d6cb9390fb86" system_variables="" />
      <row explicit_initialization="" file_name="autotest/codetest_perception.xml" on_enter_tree="onEnter" on_exit_tree="" on_release_tree="" on_request_tree="" on_update_tree="" subbrain_id="4e0976c0-6126-62ea-f7f1-c04e3942cc83" system_variables="" />
      <row explicit_initialization="" file_name="final/sa_lane_battle.xml" on_enter_tree="onCombatLaneEnter" on_exit_tree="onCombatLaneExit" on_release_tree="onCombatLaneRelease" on_request_tree="onCombatLaneRequest" on_update_tree="onCombatLaneUpdate" subbrain_id="4e1081d6-9e95-7ac6-974f-dc321d6ff9a0" system_variables="" />
      <row explicit_initialization="" file_name="_jarda/sa_test_graphSearch_jarda.xml" on_enter_tree="" on_exit_tree="" on_release_tree="" on_request_tree="" on_update_tree="onUpdate" subbrain_id="4e1eb771-d67b-4782-eec2-4a5a136d25a5" system_variables="True" />
      <row explicit_initialization="" file_name="final/sa_line_combat.xml" on_enter_tree="" on_exit_tree="" on_release_tree="" on_request_tree="" on_update_tree="onUpdate" subbrain_id="4e2978be-a9d6-615c-97a7-ccc66cae339d" system_variables="" />
      <row explicit_initialization="" file_name="final/sa_prison.xml" on_enter_tree="" on_exit_tree="" on_release_tree="" on_request_tree="" on_update_tree="onUpdate" subbrain_id="4e6eb2ee-1ef9-8ebb-a96b-7488a83c3096" system_variables="" />
      <row explicit_initialization="True" file_name="final/sa_bathhouse.xml" on_enter_tree="" on_exit_tree="" on_release_tree="" on_request_tree="" on_update_tree="onUpdate" subbrain_id="4e80c5da-7c2f-5c91-d8c1-ef4f83e69ea8" system_variables="" />
      <row explicit_initialization="" file_name="_ml/sa_test_wood_trigger.xml" on_enter_tree="" on_exit_tree="" on_release_tree="" on_request_tree="" on_update_tree="onUpdate" subbrain_id="4ea58337-aaad-0283-5ba4-17a7f2b69e9b" system_variables="" />
      <row explicit_initialization="" file_name="final/sa_land.xml" on_enter_tree="onEnterCatchSA" on_exit_tree="" on_release_tree="" on_request_tree="" on_update_tree="" subbrain_id="4ec9d16f-1c43-bcf5-97a8-de372445af87" system_variables="" />
      <row explicit_initialization="" file_name="_mz/sa_test_pursuit.xml" on_enter_tree="" on_exit_tree="" on_release_tree="" on_request_tree="" on_update_tree="onUpdate" subbrain_id="4ed9bf2f-bf96-fc7c-b0c4-d3cbae250db5" system_variables="" />
      <row explicit_initialization="" file_name="final/sa_monastery_frateria.xml" on_enter_tree="" on_exit_tree="" on_release_tree="" on_request_tree="" on_update_tree="" subbrain_id="4eef195e-f845-375c-a9db-566a0c5fe7b8" system_variables="" />
      <row explicit_initialization="" file_name="_j/sa_focus_stealth.xml" on_enter_tree="" on_exit_tree="" on_release_tree="" on_request_tree="" on_update_tree="onUpdate" subbrain_id="4ef72c39-8145-3d54-8143-07fe9b8a97a5" system_variables="" />
      <row explicit_initialization="" file_name="autotest/codetest_combat.xml" on_enter_tree="onEnter" on_exit_tree="" on_release_tree="" on_request_tree="" on_update_tree="" subbrain_id="4f2103df-911a-15c3-a54a-d1b27a708cbe" system_variables="" />
      <row explicit_initialization="" file_name="final/sa_stable.xml" on_enter_tree="" on_exit_tree="" on_release_tree="" on_request_tree="" on_update_tree="onUpdate" subbrain_id="4f61dacc-2f96-8639-9db0-5ddbea12ca99" system_variables="" />
      <row explicit_initialization="" file_name="final/sa_dynamicTrespassLevel.xml" on_enter_tree="" on_exit_tree="" on_release_tree="onUpdate" on_request_tree="" on_update_tree="" subbrain_id="4f797363-b5d9-4744-838b-a8824844b8ec" system_variables="" />
      <row explicit_initialization="" file_name="final/archery_tourney.xml" on_enter_tree="" on_exit_tree="" on_release_tree="" on_request_tree="" on_update_tree="onUpdate" subbrain_id="4f8cb063-9c61-8d3d-559f-3e46e2109caa" system_variables="" />
      <row explicit_initialization="" file_name="autotest/loadtest_messages.xml" on_enter_tree="entr" on_exit_tree="" on_release_tree="" on_request_tree="" on_update_tree="updt" subbrain_id="4f8df174-db74-0e6b-6af4-235535dbdeb6" system_variables="" />
      <row explicit_initialization="" file_name="autotest/codetest_dialogs.xml" on_enter_tree="" on_exit_tree="" on_release_tree="" on_request_tree="" on_update_tree="codetest_Dialog_onUpdate" subbrain_id="4fbd2f75-5157-ebc2-1979-8603c04a87a4" system_variables="" />
      <row explicit_initialization="" file_name="_mz/sa_placeholder.xml" on_enter_tree="" on_exit_tree="" on_release_tree="" on_request_tree="" on_update_tree="" subbrain_id="4fce7102-922b-7a70-d0b6-852dd20e1580" system_variables="" />
      <row explicit_initialization="" file_name="_common/sa_test_running.xml" on_enter_tree="" on_exit_tree="" on_release_tree="" on_request_tree="" on_update_tree="onUpdate" subbrain_id="4ff749e2-eb05-afec-b3f2-04251300db8d" system_variables="" />
      <row explicit_initialization="" file_name="final/sa_compoundwork.xml" on_enter_tree="" on_exit_tree="" on_release_tree="" on_request_tree="" on_update_tree="campOnUpdate" subbrain_id="52a55e52-b4ce-4d98-abdf-1f9f860e2d14" system_variables="" />
      <row explicit_initialization="" file_name="final/dynamic.xml" on_enter_tree="dynamic_on_enter" on_exit_tree="dynamic_on_exit" on_release_tree="" on_request_tree="" on_update_tree="dynamic_on_update" subbrain_id="530cc8a5-1ef0-45aa-99f4-de8a7288e7c2" system_variables="" />
      <row explicit_initialization="" file_name="autotest/test_numoperation.xml" on_enter_tree="" on_exit_tree="" on_release_tree="" on_request_tree="" on_update_tree="" subbrain_id="550797cb-1613-4cf7-a444-3237d840d19b" system_variables="" />
      <row explicit_initialization="" file_name="jarda/jardaAraeTest.xml" on_enter_tree="ja_onEnter" on_exit_tree="ja_onExit" on_release_tree="ja_onRelease" on_request_tree="ja_onRequest" on_update_tree="ja_onUpdate" subbrain_id="55a75ceb-a81e-4914-94f2-40f0192197c9" system_variables="" />
      <row explicit_initialization="" file_name="final/so_door.xml" on_enter_tree="player_enter" on_exit_tree="player_leave" on_release_tree="" on_request_tree="" on_update_tree="" subbrain_id="58d3b041-4c1f-43b3-b7ef-72cd35d0dd5c" system_variables="" />
      <row explicit_initialization="" file_name="final/sa_swordTournament.xml" on_enter_tree="" on_exit_tree="" on_release_tree="" on_request_tree="" on_update_tree="onUpdate" subbrain_id="5ed90264-888e-4d1f-988a-654c9fcec780" system_variables="" />
      <row explicit_initialization="" file_name="final/emptyWork.xml" on_enter_tree="" on_exit_tree="" on_release_tree="" on_request_tree="" on_update_tree="" subbrain_id="65eaa4f3-ca18-433f-a8a2-28654ad3dd23" system_variables="" />
      <row explicit_initialization="" file_name="_testing/codetest_ifcondition.xml" on_enter_tree="enter" on_exit_tree="" on_release_tree="" on_request_tree="" on_update_tree="" subbrain_id="68181c3e-7964-4233-bc18-b3098ce21421" system_variables="" />
      <row explicit_initialization="" file_name="final/npc_rychtar.xml" on_enter_tree="" on_exit_tree="" on_release_tree="" on_request_tree="" on_update_tree="" subbrain_id="68533b09-b0d9-41e7-8af2-716e558056fd" system_variables="" />
      <row explicit_initialization="" file_name="final/sa_warcamp.xml" on_enter_tree="" on_exit_tree="duel_onExit" on_release_tree="duel_onRelease" on_request_tree="duel_onRequest" on_update_tree="duel_onUpdate" subbrain_id="6aafacf6-9336-4222-b548-eec69411f8d2" system_variables="" />
      <row explicit_initialization="" file_name="final/sa_npc_shooting_range.xml" on_enter_tree="player_enter" on_exit_tree="player_exit" on_release_tree="" on_request_tree="" on_update_tree="" subbrain_id="6b72a81b-bd79-42d6-b527-e1ac42d5f321" system_variables="" />
      <row explicit_initialization="" file_name="_athert/test_event_prepadeni.xml" on_enter_tree="onEnter" on_exit_tree="onExit" on_release_tree="onRelease" on_request_tree="onRequest" on_update_tree="onUpdate" subbrain_id="72f8fed4-eb41-4fc3-bf16-dbdb24232797" system_variables="" />
      <row explicit_initialization="" file_name="final/sa_pub_v3.xml" on_enter_tree="onEnter" on_exit_tree="onExit" on_release_tree="onRelease" on_request_tree="onRequest" on_update_tree="onUpdate" subbrain_id="78a0008e-39ad-4be6-a8a7-1db60975be6f" system_variables="True" />
      <row explicit_initialization="" file_name="final/sa_warcamp.xml" on_enter_tree="warCamp_onEnter" on_exit_tree="" on_release_tree="warCamp_onRelease" on_request_tree="warCamp_onRequest" on_update_tree="warCamp_onUpdate" subbrain_id="7a30b620-04e3-49c7-b5fb-c87fce76a5c9" system_variables="" />
      <row explicit_initialization="" file_name="final/sa_warehouse.xml" on_enter_tree="" on_exit_tree="" on_release_tree="" on_request_tree="" on_update_tree="" subbrain_id="7f0201d0-5ff2-4e3a-aba9-73052ae0f431" system_variables="" />
      <row explicit_initialization="" file_name="_testing/test_msg.xml" on_enter_tree="" on_exit_tree="" on_release_tree="" on_request_tree="req" on_update_tree="upd" subbrain_id="8065f454-af1f-4e6d-b92b-e747b9c62b13" system_variables="" />
      <row explicit_initialization="" file_name="_vachek/sa_test_vachek.xml" on_enter_tree="" on_exit_tree="" on_release_tree="" on_request_tree="" on_update_tree="" subbrain_id="80d64c30-a155-4aa2-a178-e61879c9a8c8" system_variables="" />
      <row explicit_initialization="" file_name="_malac/test_sa_2_malac.xml" on_enter_tree="test_sa_2_on_enter" on_exit_tree="test_sa_2_on_exit" on_release_tree="test_sa_2_on_release" on_request_tree="test_sa_2_on_request" on_update_tree="test_sa_2_on_update" subbrain_id="80e03dd8-f2c1-4af7-b322-3acca51ee10e" system_variables="" />
      <row explicit_initialization="" file_name="_j/cquery.xml" on_enter_tree="" on_exit_tree="" on_release_tree="" on_request_tree="" on_update_tree="" subbrain_id="835aeab7-1f4b-4d33-bc0c-d51365fbbd30" system_variables="" />
      <row explicit_initialization="" file_name="final/sa_archeryTutorial.xml" on_enter_tree="" on_exit_tree="" on_release_tree="" on_request_tree="" on_update_tree="onUpdate" subbrain_id="861fc333-0f40-47df-a324-9a676681bb1f" system_variables="" />
      <row explicit_initialization="" file_name="final/sa_spa.xml" on_enter_tree="" on_exit_tree="" on_release_tree="" on_request_tree="" on_update_tree="" subbrain_id="87e841aa-02b0-4020-8cf4-c84931635868" system_variables="" />
      <row explicit_initialization="" file_name="final/sa_dlc_homes.xml" on_enter_tree="" on_exit_tree="" on_release_tree="" on_request_tree="" on_update_tree="onUpdate" subbrain_id="886349c9-c083-43c4-a0e3-ca10726a35ec" system_variables="" />
      <row explicit_initialization="" file_name="_testing/test_walkaround.xml" on_enter_tree="" on_exit_tree="" on_release_tree="" on_request_tree="walkaround_onRequest" on_update_tree="walkaround_onUpdate" subbrain_id="8b0d81f6-079d-405d-94d2-b364a518cd42" system_variables="" />
      <row explicit_initialization="" file_name="_athert/codetest_parallel.xml" on_enter_tree="Parall_onEnter" on_exit_tree="" on_release_tree="" on_request_tree="" on_update_tree="" subbrain_id="8e8e1099-d149-4730-90a5-66db8eb00ebe" system_variables="" />
      <row explicit_initialization="" file_name="final/sa_npc_shooting_range.xml" on_enter_tree="" on_exit_tree="" on_release_tree="OnRelease" on_request_tree="" on_update_tree="" subbrain_id="8f18689f-0d81-4352-96a9-eacbef8a668c" system_variables="" />
      <row explicit_initialization="" file_name="final/sa_quarry.xml" on_enter_tree="" on_exit_tree="" on_release_tree="" on_request_tree="" on_update_tree="" subbrain_id="9274a79d-213f-4782-98d0-bd2703f97a0a" system_variables="" />
      <row explicit_initialization="" file_name="final/sa_miller.xml" on_enter_tree="" on_exit_tree="" on_release_tree="" on_request_tree="" on_update_tree="onUpdate" subbrain_id="932bcf8c-8899-4e4c-bd96-34fa593fb03e" system_variables="" />
      <row explicit_initialization="" file_name="autotest/smartarea.xml" on_enter_tree="" on_exit_tree="" on_release_tree="" on_request_tree="" on_update_tree="" subbrain_id="9448dd2e-5b2d-4d0f-9307-b36e05f09cef" system_variables="" />
      <row explicit_initialization="" file_name="autotest/codeTest_FetchLinks.xml" on_enter_tree="Flink_onEnter" on_exit_tree="" on_release_tree="" on_request_tree="" on_update_tree="" subbrain_id="94d988b2-9fa4-40a1-a4be-9e9317f7ef05" system_variables="" />
      <row explicit_initialization="" file_name="_athert/testMoveDistance.xml" on_enter_tree="" on_exit_tree="" on_release_tree="" on_request_tree="" on_update_tree="onUpdate" subbrain_id="99410842-6bcf-4db8-adfe-bc7be596ecc7" system_variables="" />
      <row explicit_initialization="" file_name="final/sa_militaryCamp.xml" on_enter_tree="militaryCamp_onEnter" on_exit_tree="" on_release_tree="militaryCamp_onRelease" on_request_tree="militaryCamp_onRequest" on_update_tree="militaryCamp_onUpdate" subbrain_id="9ad75dbd-c4c9-4724-ae01-6699c60a1f8e" system_variables="" />
      <row explicit_initialization="" file_name="final/sa_castle.xml" on_enter_tree="" on_exit_tree="" on_release_tree="" on_request_tree="" on_update_tree="" subbrain_id="9def4cc6-a65c-48c9-88db-f3f76b7b3f03" system_variables="" />
      <row explicit_initialization="" file_name="final/Sheep.xml" on_enter_tree="lost_enter" on_exit_tree="" on_release_tree="" on_request_tree="" on_update_tree="" subbrain_id="a3457758-be2a-4937-b4c2-35772ab2a4cf" system_variables="" />
      <row explicit_initialization="" file_name="_qa/test_archery.xml" on_enter_tree="onEnter" on_exit_tree="" on_release_tree="" on_request_tree="" on_update_tree="onUpdate" subbrain_id="a65a27d6-422b-4633-8bf1-874fc4450c79" system_variables="" />
      <row explicit_initialization="" file_name="_athert/test_Budgets.xml" on_enter_tree="" on_exit_tree="" on_release_tree="" on_request_tree="" on_update_tree="tba_onUpdate" subbrain_id="a6c57e8e-07cb-46b8-b848-aacbbc8233a9" system_variables="" />
      <row explicit_initialization="" file_name="final/sa_camp2.xml" on_enter_tree="" on_exit_tree="" on_release_tree="" on_request_tree="" on_update_tree="onUpdate" subbrain_id="ac709169-d508-41f1-b8e2-d2fcd9e299f8" system_variables="True" />
      <row explicit_initialization="" file_name="_dan/sa_test_dan.xml" on_enter_tree="" on_exit_tree="" on_release_tree="" on_request_tree="" on_update_tree="onUpdate" subbrain_id="b2cb7e4d-0489-4b56-9eeb-a0f59da1195f" system_variables="" />
      <row explicit_initialization="" file_name="final/sa_study.xml" on_enter_tree="" on_exit_tree="" on_release_tree="" on_request_tree="" on_update_tree="" subbrain_id="b5427471-ecb7-465d-b4c1-2af8e34e832c" system_variables="" />
      <row explicit_initialization="" file_name="_testing/test_movement_three_points.xml" on_enter_tree="" on_exit_tree="" on_release_tree="" on_request_tree="" on_update_tree="" subbrain_id="b59ac74e-690f-4872-9529-ca093adbbcfd" system_variables="" />
      <row explicit_initialization="" file_name="_mff.ai/Guard.xml" on_enter_tree="" on_exit_tree="" on_release_tree="" on_request_tree="SA_Guard_onRequest" on_update_tree="SA_Guard_onUpdate" subbrain_id="c12c17ce-3f2e-43ca-86ae-18ab5bc88342" system_variables="" />
      <row explicit_initialization="" file_name="final/sa_pubComp.xml" on_enter_tree="" on_exit_tree="" on_release_tree="" on_request_tree="" on_update_tree="" subbrain_id="c3286f73-b5d3-4460-95a4-899854914726" system_variables="" />
      <row explicit_initialization="" file_name="_athert/test_siege.xml" on_enter_tree="" on_exit_tree="" on_release_tree="sg_onRls" on_request_tree="sg_onReq" on_update_tree="sg_onUpd" subbrain_id="c34e984b-2697-43b6-bfbf-63ddb72d8037" system_variables="" />
      <row explicit_initialization="" file_name="_quasimodo/test_var_operations.xml" on_enter_tree="" on_exit_tree="" on_release_tree="" on_request_tree="" on_update_tree="" subbrain_id="c5f42e16-b2b6-444c-8ce3-8bf0cacf95c7" system_variables="" />
      <row explicit_initialization="" file_name="final/sa_q_waldensians.xml" on_enter_tree="" on_exit_tree="" on_release_tree="" on_request_tree="" on_update_tree="" subbrain_id="ccf902f9-e230-4b2f-8315-b6163cc472bf" system_variables="" />
      <row explicit_initialization="" file_name="final/sa_church.xml" on_enter_tree="" on_exit_tree="" on_release_tree="onRelease" on_request_tree="onRequest" on_update_tree="onUpdate" subbrain_id="cd356a0b-137f-4b21-8a77-60688b237768" system_variables="" />
      <row explicit_initialization="" file_name="final/hunter.xml" on_enter_tree="" on_exit_tree="" on_release_tree="" on_request_tree="" on_update_tree="tannery_update" subbrain_id="cd3ef5e2-d90e-4459-a500-6378ce7ddec9" system_variables="" />
      <row explicit_initialization="" file_name="final/backgammon.xml" on_enter_tree="" on_exit_tree="" on_release_tree="" on_request_tree="" on_update_tree="" subbrain_id="d8a700cc-3e83-43ee-884f-d34027643b83" system_variables="" />
      <row explicit_initialization="" file_name="_athert/sa_combatTorchTest.xml" on_enter_tree="" on_exit_tree="" on_release_tree="" on_request_tree="" on_update_tree="onUpdate" subbrain_id="d90376b0-2872-4199-8cf0-c3b9e27e25cb" system_variables="" />
      <row explicit_initialization="" file_name="final/sa_apothecary.xml" on_enter_tree="" on_exit_tree="" on_release_tree="" on_request_tree="" on_update_tree="" subbrain_id="da3c1cea-7f9c-4447-9456-05f0b276abc5" system_variables="" />
      <row explicit_initialization="" file_name="autotest/CorridorNew.xml" on_enter_tree="" on_exit_tree="" on_release_tree="" on_request_tree="" on_update_tree="" subbrain_id="e17b470a-76d4-45db-a56e-6ba5205a0ab6" system_variables="" />
      <row explicit_initialization="" file_name="autotest/codeTest_FuseBox.xml" on_enter_tree="FuseBox_onEnter" on_exit_tree="" on_release_tree="" on_request_tree="" on_update_tree="" subbrain_id="e3013f4a-7c81-4828-a240-20bf4e30dfee" system_variables="" />
      <row explicit_initialization="" file_name="final/activityHorceRace.xml" on_enter_tree="sa_onEnter" on_exit_tree="" on_release_tree="" on_request_tree="" on_update_tree="sa_onUpdate" subbrain_id="e88954b5-f73c-4003-8b94-b7a2654d16d9" system_variables="" />
      <row explicit_initialization="" file_name="_martin_cerny/combat_simulator.xml" on_enter_tree="" on_exit_tree="" on_release_tree="" on_request_tree="" on_update_tree="sa_update" subbrain_id="f104416d-de41-4e59-a511-8a59eec9ddd1" system_variables="" />
      <row explicit_initialization="" file_name="_athert/test_sa_athert.xml" on_enter_tree="" on_exit_tree="" on_release_tree="" on_request_tree="" on_update_tree="test_sa_onUpdate" subbrain_id="f13ac3de-df86-42b4-9b7d-a87f2dc81a6d" system_variables="" />
    </rows>
  </table>
</database>
